{
	"name": "Legacy_HTM_AccountType",
	"properties": {
		"linkedServiceName": {
			"referenceName": "modineerworkspace-WorkspaceDefaultStorage",
			"type": "LinkedServiceReference"
		},
		"folder": {
			"name": "HTM"
		},
		"annotations": [],
		"type": "Json",
		"typeProperties": {
			"location": {
				"type": "AzureBlobFSLocation",
				"fileName": {
					"value": "@concat('accounttype-',guid())",
					"type": "Expression"
				},
				"folderPath": "legacy-htm/account-type",
				"fileSystem": "unified-data-cluster"
			}
		},
		"schema": {}
	},
	"type": "Microsoft.Synapse/workspaces/datasets"
}